nonebot_plugin_lolmatch/__init__.py
nonebot_plugin_lolmatch/config.py
nonebot_plugin_lolmatch/data_source.py
nonebot_plugin_lolmatch/migrations/54eff20f9cc8_init_db.py
nonebot_plugin_lolmatch/migrations/__init__.py
nonebot_plugin_lolmatch/model.py
nonebot_plugin_lolmatch/short.css
nonebot_plugin_lolmatch/template.py
nonebot_plugin_lolmatch-0.4.0.dist-info/LICENSE
nonebot_plugin_lolmatch-0.4.0.dist-info/METADATA
nonebot_plugin_lolmatch-0.4.0.dist-info/WHEEL
nonebot_plugin_lolmatch-0.4.0.dist-info/RECORD
