Metadata-Version: 2.1
Name: nonebot_plugin_lolmatch
Version: 0.4.0
Summary: 
Home-page: https://github.com/MaxCrazy1101/nonebot_plugin_lolmatch
License: MIT
Keywords: nonebot,nonebot2,LoL
Author: Alex Newton
Author-email: sharenfan222@gmail.com
Requires-Python: >=3.8,<4.0.0
Classifier: License :: OSI Approved :: MIT License
Classifier: Programming Language :: Python :: 3
Classifier: Programming Language :: Python :: 3.8
Classifier: Programming Language :: Python :: 3.9
Classifier: Programming Language :: Python :: 3.10
Classifier: Programming Language :: Python :: 3.11
Classifier: Programming Language :: Python :: 3.12
Classifier: Programming Language :: Python :: 3.13
Requires-Dist: aiohttp (>=3.10.0)
Requires-Dist: nonebot-plugin-orm (>=0.7.0,<1.0.0)
Requires-Dist: nonebot2 (>=2.2.0,<3.0.0)
Requires-Dist: nonebot_plugin_apscheduler (>=0.4.0,<2.0.0)
Requires-Dist: nonebot_plugin_htmlrender (>=0.3.0,<1.0.0)
Requires-Dist: pillow (>=8)
Requires-Dist: ujson (>=5,<6)
Project-URL: Repository, https://github.com/MaxCrazy1101/nonebot_plugin_lolmatch
